{
  "total_cells": 20,
  "cell_counts": {
    "RBC": 20
  },
  "cell_percentages": {
    "RBC": 100.0
  },
  "feature_stats": {
    "RBC": {
      "avg_area": 2694.125,
      "avg_perimeter": 385.4938764333725,
      "avg_circularity": 0.2733746343521526,
      "avg_texture": 8.944019720599332
    }
  },
  "warnings": [
    "\u26a0\ufe0f WBC critically low: 0 cells (0.0%) - Could indicate severe immunosuppression",
    "\u26a0\ufe0f Platelets critically low: 0 cells (0.0%) - Could indicate thrombocytopenia"
  ]
}